{
  "name": "improved-chat",
  "title": "Improved Chat",
  "description": "Makes the chat better, FG-style",
  "version": "1.0.2",
  "minimumCoreVersion": "0.8.0",
  "compatibleCoreVersion": "0.8.8",
  "author": "Shekkie",
  "esmodules": [
    "./improved-chat.js"
  ],
  "scripts": [
  ],
  "styles": [
  ],
  "languages": [
  ],
  "url": "https://github.com/laudrim6192/fvtt-improved-chat",
  "manifest": "https://github.com/laudrim6192/fvtt-improved-chat/releases/latest/download/module.json",
  "download": "https://github.com/laudrim6192/fvtt-improved-chat/releases/latest/download/module.zip"
}
